http_mcp/__init__.py
http_mcp/_stdio_transport.py
http_mcp/_transport_base.py
http_mcp/_transport_http.py
http_mcp/_transport_types.py
http_mcp/exceptions.py
http_mcp/py.typed
http_mcp/server.py
http_mcp/server_interface.py
http_mcp/mcp_types/__init__.py
http_mcp/mcp_types/capabilities.py
http_mcp/mcp_types/content.py
http_mcp/mcp_types/messages.py
http_mcp/mcp_types/prompts.py
http_mcp/mcp_types/tools.py
http_mcp/types/__init__.py
http_mcp/types/models.py
http_mcp/types/prompts.py
http_mcp/types/tools.py
http_mcp/types/utils.py
http_mcp-0.8.1.dist-info/METADATA
http_mcp-0.8.1.dist-info/WHEEL
http_mcp-0.8.1.dist-info/licenses/LICENSE
http_mcp-0.8.1.dist-info/RECORD
