Metadata-Version: 2.4
Name: http-mcp
Version: 0.8.1
Summary: This is a HTTP implementation of the MCP protocol
Project-URL: Homepage, https://github.com/yeison-liscano/http_mcp
Project-URL: Issues, https://github.com/yeison-liscano/http_mcp/issues
Author-email: Yeison Liscano <yliscanoc@gmail.com>
Maintainer-email: Yeison Liscano <yliscanoc@gmail.com>
License-Expression: MIT
License-File: LICENSE
Keywords: automation,http,llm,mcp
Classifier: Intended Audience :: Developers
Classifier: Operating System :: OS Independent
Classifier: Programming Language :: Python :: 3
Classifier: Programming Language :: Python :: 3.10
Classifier: Programming Language :: Python :: 3.11
Classifier: Programming Language :: Python :: 3.12
Classifier: Programming Language :: Python :: 3.13
Requires-Python: >=3.10
Requires-Dist: pydantic==2.12.5
Requires-Dist: starlette==0.50.0
Requires-Dist: uvicorn==0.38.0
